README.md
setup.py
IDEA_SESIT_NEW.egg-info/PKG-INFO
IDEA_SESIT_NEW.egg-info/SOURCES.txt
IDEA_SESIT_NEW.egg-info/dependency_links.txt
IDEA_SESIT_NEW.egg-info/top_level.txt
copper/__init__.py
copper/copper_data_summary.py
copper/copper_extension.py
copper/copper_results.py
copper/plot_installed_capacity.py
main/Combined_Visualization_Current.py
main/__init__.py
main/OSeMOSYS/OSeMOSYS.py
main/OSeMOSYS/__init__.py
main/OSeMOSYS/format_data.py
main/Panel_app/Combined_Visualization.py
main/Panel_app/__init__.py
postprocess_scripts/COPPER_Data_analyze_v4.py
postprocess_scripts/__init__.py
postprocess_scripts/SILVER_postprocess/SILVER_Post_Process_app.py
postprocess_scripts/SILVER_postprocess/__init__.py
postprocess_scripts/SILVER_postprocess/query_SILVER.py