Metadata-Version: 2.1
Name: IDEA-SESIT-NEW
Version: 0.0.1
Summary: Integrated Dashboard for Energy transition Analysis
Home-page: UNKNOWN
Author: Mark He
Author-email: hexuanheng@gmail.com
License: UNKNOWN
Platform: UNKNOWN
Classifier: Intended Audience :: Developers
Classifier: Programming Language :: Python :: 3
Classifier: Operating System :: Unix
Classifier: Operating System :: MacOS :: MacOS X
Classifier: Operating System :: Microsoft :: Windows
Requires-Python: >=3.6
